{
  "version": "0.2",
  "language": "en",
  "import": ["@cspell/dict-npm/cspell-ext.json"],
  "ignorePaths": [
    "**/*.lock",
    "**/*.txt",
    "pnpm-lock.yaml",
    "dist-jsr",
    "dist-npm",
    "tests-runtime"
  ],
  "words": [
    "alacritty",
    "alternar",
    "anykey",
    "Approximative",
    "appts",
    "arethetypeswrong",
    "Arryn",
    "astro",
    "astrowind",
    "attw",
    "ausgewählt",
    "authjs",
    "avez",
    "Baratheon",
    "blefnk",
    "bleverse",
    "bootstrapper",
    "bootstrappers",
    "browserlist",
    "browserlistrc",
    "Brun",
    "bumpp",
    "bunp",
    "bunx",
    "choisi",
    "Clooney",
    "cmder",
    "Codemod",
    "confirmtoggle",
    "continuar",
    "cristal",
    "cronvel",
    "datepart",
    "dateparts",
    "deafult",
    "defu",
    "deno",
    "derhuerst",
    "Deutsch",
    "dflt",
    "Doesnt",
    "Dont",
    "Downey",
    "ecommerce",
    "emojify",
    "envjs",
    "eslintcache",
    "favourite",
    "figliolia",
    "Fireship",
    "Focusable",
    "forgetme",
    "frontends",
    "Geralt",
    "goroutines",
    "Greyjoy",
    "Griptape",
    "Gyllenhaal",
    "haben",
    "Haha",
    "headlessly",
    "hoverable",
    "iife",
    "invertir",
    "jetbrains",
    "język",
    "jiejie",
    "jumpstart",
    "keypresses",
    "Kornienko",
    "Korniienko",
    "Lannister",
    "lazyness",
    "lockb",
    "LOGLIB",
    "madrun",
    "magicast",
    "Martell",
    "Mikey",
    "Misrefactored",
    "mkdist",
    "Mkey",
    "montag",
    "Nazar",
    "Nazarii",
    "nenc",
    "nocheck",
    "nodenext",
    "Noninteractive",
    "npmjs",
    "ntqry",
    "nuqs",
    "nypm",
    "ofetch",
    "onwidget",
    "optim",
    "optionception",
    "outro",
    "pagedown",
    "pageup",
    "picocolors",
    "planetscale",
    "pmndrs",
    "polski",
    "Preconfigured",
    "printj",
    "QAZWSXEDCRFVTGBYHNUJMIKOLP",
    "rawlist",
    "reli",
    "relinka",
    "Relivator",
    "reliverse",
    "Reliversing",
    "Rivia",
    "rxvt",
    "sbuf",
    "selección",
    "seleccionar",
    "sentencer",
    "shadcn",
    "signup",
    "Silverhand",
    "sisteransi",
    "Sprache",
    "subchoices",
    "superapp",
    "Targ",
    "Targaryen",
    "tasuku",
    "terkelg",
    "termkit",
    "tseslint",
    "Tully",
    "turso",
    "typebox",
    "typecheck",
    "typesafe",
    "typesafety",
    "typestat",
    "Tyrell",
    "unjs",
    "unkey",
    "unpub",
    "unstub",
    "UPLOADTHING",
    "valign",
    "venv",
    "versator",
    "Vous",
    "vsprintf",
    "Whoo",
    "Wybrałeś",
    "Yadxh",
    "ytrewq",
    "обрали",
    "Українська",
    "українську"
  ]
}
